pop_projection/Actuariat.py
pop_projection/Cashflows.py
pop_projection/Effectifs.py
pop_projection/Groupes.py
pop_projection/__init__.py
pop_projection/sample_laws.py
pop_projection/tools.py
pop_projection/data/children.csv
pop_projection/data/employees - Copie.csv
pop_projection/data/employees.csv
pop_projection/data/globnum.csv
pop_projection/data/pensions.csv
pop_projection/data/rate_contr.csv
pop_projection/data/salaries.csv
pop_projection/data/spouses.csv
pop_projection/test/__init__.py
pop_projection/test/asupprimer.py
pop_projection/test/test_Effectifs.py
pop_projection/test/data/children.csv
pop_projection/test/data/employees.csv
pop_projection/test/data/spouses.csv
pop_projection-3.0.0.dist-info/METADATA
pop_projection-3.0.0.dist-info/WHEEL
pop_projection-3.0.0.dist-info/top_level.txt
pop_projection-3.0.0.dist-info/RECORD
