Metadata-Version: 2.1
Name: pop_projection
Version: 3.0.0
Summary: Projection of population of a retirement plan.
Home-page: https://github.com/ateffal/pop_projection
Author: Amine TEFFAL
Author-email: a.teffal@gmail.com
License: UNKNOWN
Platform: UNKNOWN
Classifier: Programming Language :: Python :: 3
Classifier: License :: OSI Approved :: MIT License
Classifier: Operating System :: OS Independent
